simulate_replay/LFP.py
simulate_replay/__init__.py
simulate_replay/behavior.py
simulate_replay/multiunit.py
simulate_replay/simulate_dataset.py
simulate_replay/spiking.py
simulate_replay-0.1.0.dist-info/LICENSE
simulate_replay-0.1.0.dist-info/METADATA
simulate_replay-0.1.0.dist-info/WHEEL
simulate_replay-0.1.0.dist-info/top_level.txt
simulate_replay-0.1.0.dist-info/RECORD
