Metadata-Version: 2.1
Name: simulate-replay
Version: 0.1.0
Summary: Simulate replay dataset
Home-page: https://github.com/Eden-Kramer-Lab/simulate_replay
Author: Eric Denovellis
Author-email: edeno@bu.edu
License: MIT
Platform: UNKNOWN
Requires-Dist: numpy (>=1.14)
Requires-Dist: scipy
Requires-Dist: pandas
Requires-Dist: matplotlib
